MANIFEST.in
setup.cfg
setup.py
bitfusion/VERSION
bitfusion/__init__.py
bitfusion/bfapi.py
bitfusion/errors.py
bitfusion.egg-info/PKG-INFO
bitfusion.egg-info/SOURCES.txt
bitfusion.egg-info/dependency_links.txt
bitfusion.egg-info/requires.txt
bitfusion.egg-info/top_level.txt
bitfusion/api/__init__.py
bitfusion/api/base.py
bitfusion/api/code.py
bitfusion/api/data.py
bitfusion/api/gpu.py
bitfusion/api/job.py
bitfusion/api/node.py
bitfusion/api/project.py
bitfusion/api/resource.py
bitfusion/api/user.py
bitfusion/api/volume.py
bitfusion/api/workspace.py
bitfusion/lib/__init__.py
bitfusion/lib/files.py
bitfusion/lib/session.py
bitfusion/lib/time.py