Metadata-Version: 1.0
Name: bitfusion
Version: 1.0.4
Summary: Python SDK for developing against the Bitfusion Platform
Home-page: http://www.bitfusion.io
Author: Brian Schultz
Author-email: brian@bitfusion.io
License: UNKNOWN
Platform: UNKNOWN
